[
  {
    "id": "f0abe7ca-e21d-4cf1-b3ce-308afb18be5e",
    "data": [
      {
        "text": "how is ",
        "userDefined": false
      },
      {
        "text": "cricket",
        "alias": "cricket",
        "meta": "@sys.any",
        "userDefined": true
      },
      {
        "text": " played",
        "userDefined": false
      }
    ],
    "isTemplate": false,
    "count": 0,
    "updated": 0
  },
  {
    "id": "0167ad23-fd5f-4413-b97c-e1f0dfd003d8",
    "data": [
      {
        "text": "cricket",
        "alias": "cricket",
        "meta": "@sys.any",
        "userDefined": true
      }
    ],
    "isTemplate": false,
    "count": 0,
    "updated": 0
  },
  {
    "id": "6b64f39b-e53d-4d69-9d4d-77749113a7d3",
    "data": [
      {
        "text": "how to play ",
        "userDefined": false
      },
      {
        "text": "cricket",
        "alias": "cricket",
        "meta": "@sys.any",
        "userDefined": true
      }
    ],
    "isTemplate": false,
    "count": 0,
    "updated": 0
  },
  {
    "id": "d48bbab8-92f5-44a6-b029-d45d0e03215e",
    "data": [
      {
        "text": "what is the meaning of ",
        "userDefined": false
      },
      {
        "text": "cricket",
        "alias": "cricket",
        "meta": "@sys.any",
        "userDefined": true
      }
    ],
    "isTemplate": false,
    "count": 0,
    "updated": 0
  },
  {
    "id": "7bed85ec-ec90-484e-b637-234008c93300",
    "data": [
      {
        "text": "what is ",
        "userDefined": false
      },
      {
        "text": "cricket",
        "alias": "cricket",
        "meta": "@sys.any",
        "userDefined": true
      }
    ],
    "isTemplate": false,
    "count": 0,
    "updated": 0
  },
  {
    "id": "1f14cdf1-63b8-47b5-93c7-e663793edee7",
    "data": [
      {
        "text": "tell me something about ",
        "userDefined": false
      },
      {
        "text": "cricket",
        "alias": "cricket",
        "meta": "@sys.any",
        "userDefined": true
      }
    ],
    "isTemplate": false,
    "count": 1,
    "updated": 0
  },
  {
    "id": "4a366961-ef3b-43cf-a283-4e38c4e8b8e1",
    "data": [
      {
        "text": "tell me about ",
        "userDefined": false
      },
      {
        "text": "cricket",
        "alias": "cricket",
        "meta": "@sys.any",
        "userDefined": true
      }
    ],
    "isTemplate": false,
    "count": 0,
    "updated": 0
  }
]